synth/__init__.py
synth/_blocks.py
synth/_types.py
synth/_version.py
synth/cli.py
synth/compare.py
synth/config.py
synth/core.py
synth/covariance.py
synth/crlb.py
synth/deformation.py
synth/global_coherence.py
synth/plotting.py
synth/py.typed
synth/utils.py
synth/data/coherence_fall_amp.gti.gpkg.zip
synth/data/coherence_fall_coh12.gti.gpkg.zip
synth/data/coherence_fall_rho.gti.gpkg.zip
synth/data/coherence_fall_tau.gti.gpkg.zip
synth/data/coherence_spring_amp.gti.gpkg.zip
synth/data/coherence_spring_coh12.gti.gpkg.zip
synth/data/coherence_spring_rho.gti.gpkg.zip
synth/data/coherence_spring_tau.gti.gpkg.zip
synth/data/coherence_summer_amp.gti.gpkg.zip
synth/data/coherence_summer_coh12.gti.gpkg.zip
synth/data/coherence_summer_rho.gti.gpkg.zip
synth/data/coherence_summer_tau.gti.gpkg.zip
synth/data/coherence_winter_amp.gti.gpkg.zip
synth/data/coherence_winter_coh12.gti.gpkg.zip
synth/data/coherence_winter_rho.gti.gpkg.zip
synth/data/coherence_winter_tau.gti.gpkg.zip
synth_insar-0.1.2.dist-info/licenses/LICENSE
synth_insar-0.1.2.dist-info/METADATA
synth_insar-0.1.2.dist-info/WHEEL
synth_insar-0.1.2.dist-info/entry_points.txt
synth_insar-0.1.2.dist-info/top_level.txt
synth_insar-0.1.2.dist-info/RECORD
