Metadata-Version: 2.4
Name: synth-insar
Version: 0.1.2
Summary: Synthetic data generator for InSAR time series analysis
Author-email: Scott Staniewicz <scott.j.staniewicz@jpl.nasa.gov>
Project-URL: Homepage, https://github.com/isce-framework/synth
Project-URL: Bug Tracker, https://github.com/isce-framework/synth/issues
Project-URL: Discussions, https://github.com/isce-framework/synth/discussions
Project-URL: Changelog, https://github.com/isce-framework/synth/releases
Classifier: Intended Audience :: Developers
Classifier: Intended Audience :: Science/Research
Classifier: Programming Language :: Python :: 3
Classifier: Programming Language :: Python :: 3.11
Classifier: Programming Language :: Python :: 3.12
Classifier: Programming Language :: Python :: 3.13
Classifier: Programming Language :: Python
Classifier: Topic :: Scientific/Engineering
Classifier: Typing :: Typed
Requires-Python: >=3.11
License-File: LICENSE
Requires-Dist: troposim>=0.2.1
Requires-Dist: rasterio<2,>=1.4.3
Requires-Dist: h5py>=3.10.0
Requires-Dist: jax>=0.6.0
Requires-Dist: numpy>=2.0
Requires-Dist: pydantic>=2.6
Requires-Dist: pyproj>=3
Requires-Dist: scipy>=1.13.0
Requires-Dist: tqdm>=4.65
Dynamic: license-file
